booking_statistics/__init__.py
booking_statistics/counter.py
booking_statistics-0.1.dist-info/METADATA
booking_statistics-0.1.dist-info/WHEEL
booking_statistics-0.1.dist-info/top_level.txt
booking_statistics-0.1.dist-info/RECORD
